OxidationNumberCalculator
