Metadata-Version: 2.1
Name: OxidationNumberCalculator
Version: 1.1
Summary: An alpha version of an oxidation number calculator that can be used on compounds/Elements or Chemical Equations.
Home-page: https://www.inventorsniche.com
Author: Harold J. Iwen
Author-email: inventorsniche349@gmail.com
License: MIT
Download-URL: https://github.com/Hiwen-STEM/OxidationNumberCalculator
Keywords: Oxidation,Number,Oxidation_Number,oxidation_number,stoichiometry,chemical,equation,chemical_equation
Platform: UNKNOWN
Classifier: Development Status :: 3 - Alpha
Classifier: Intended Audience :: Developers
Classifier: Topic :: Software Development :: Build Tools
Classifier: License :: OSI Approved :: MIT License
Classifier: Programming Language :: Python :: 3.6
Classifier: Programming Language :: Python :: 3.7
Classifier: Programming Language :: Python :: 3.8
